{
    "@id": "dtmi:com:ngsi-ld:SeaPortFacilities;0",
    "@type": "Interface",
    "@context": "dtmi:dtdl:context;2",
    "comment": "Seaport facilities schema adapted to DTDL from smartdatamodels.org. Source: https://raw.githubusercontent.com/smart-data-models/dataModel.Ports/master/SeaportFacilities/schema.json",
    "description": "The Data Model is intended to provide information about ports that can accommodate pleasure craft, commerce or passenger  transport. It permit to represent the parameters of each port, its location, its mooring capacities and the free or paid services associated with it provided directly by the port or by professionals working on or near the port.",
    "displayName": "SeaPortFacilities",
    "contents": [
        {
            "name": "alternateName",
            "writable": true,
            "displayName": "alternateName",
            "@type": "Property",
            "schema": "string",
            "comment": "An alternative name for this item"
        },
        {
            "name": "areaServed",
            "writable": true,
            "displayName": "areaServed",
            "@type": "Property",
            "schema": "string",
            "comment": "The geographic area where a service or offered item is provided"
        },
        {
            "name": "dataProvider",
            "writable": true,
            "displayName": "dataProvider",
            "@type": "Property",
            "schema": "string",
            "comment": "A sequence of characters identifying the provider of the harmonised data entity."
        },
        {
            "name": "dateCreated",
            "writable": true,
            "displayName": "dateCreated",
            "@type": "Property",
            "schema": "dateTime",
            "comment": "Entity creation timestamp. This will usually be allocated by the storage platform."
        },
        {
            "name": "dateLastReported",
            "writable": true,
            "displayName": "dateLastReported",
            "@type": "Property",
            "schema": "dateTime",
            "comment": "A timestamp which denotes the last time when a flow successfully reported data. The date and time of this Repository in ISO8601 UTCformat"
        },
        {
            "name": "dateModified",
            "writable": true,
            "displayName": "dateModified",
            "@type": "Property",
            "schema": "dateTime",
            "comment": "Timestamp of the last modification of the entity. This will usually be allocated by the storage platform."
        },
        {
            "name": "description",
            "writable": true,
            "displayName": "description",
            "@type": "Property",
            "schema": "string",
            "comment": "A description of this item"
        },
        {
            "name": "name",
            "writable": true,
            "displayName": "name",
            "@type": "Property",
            "schema": "string",
            "comment": "The name of this item."
        },
        {
            "name": "refDevice",
            "writable": true,
            "displayName": "refDevice"
        },
        {
            "name": "seeAlso",
            "writable": true,
            "displayName": "seeAlso"
        },
        {
            "name": "source",
            "writable": true,
            "displayName": "source",
            "@type": "Property",
            "schema": "string",
            "comment": "A sequence of characters giving the original source of the entity data as a URL. Recommended to be the fully qualified domain name of the source provider, or the URL to the source object."
        },
        {
            "@type": "Telemetry",
            "name": "openingHoursSpecification",
            "schema": {
                "@type": "Array",
                "elementSchema": "object"
            },
            "comment": "A structured value providing information about the opening hours of a place or a certain service inside a place",
            "displayName": "openingHoursSpecification"
        },
        {
            "@type": "Telemetry",
            "name": "owner",
            "schema": {
                "@type": "Array",
                "elementSchema": "string"
            },
            "comment": "A List containing a JSON encoded sequence of characters referencing the unique Ids of the owner(s)",
            "displayName": "owner"
        },
        {
            "@type": "object",
            "name": "address",
            "comment": "The mailing address",
            "displayName": "address",
            "fields": [
                {
                    "name": "addressCountry",
                    "schema": "string"
                },
                {
                    "name": "addressLocality",
                    "schema": "string"
                },
                {
                    "name": "addressRegion",
                    "schema": "string"
                },
                {
                    "name": "postOfficeBoxNumber",
                    "schema": "string"
                },
                {
                    "name": "postalCode",
                    "schema": "string"
                },
                {
                    "name": "streetAddress",
                    "schema": "string"
                }
            ]
        },
        {
            "@type": "Telemetry",
            "name": "location_Point",
            "schema": "point"
        },
        {
            "@type": "Telemetry",
            "name": "location_LineString",
            "schema": "lineString"
        },
        {
            "@type": "Telemetry",
            "name": "location_Polygon",
            "schema": "polygon"
        },
        {
            "@type": "Telemetry",
            "name": "location_MultiPoint",
            "schema": "multiPoint"
        },
        {
            "@type": "Telemetry",
            "name": "location_MultiLineString",
            "schema": "multiLineString"
        },
        {
            "@type": "Telemetry",
            "name": "location_MultiPolygon",
            "schema": "multiPolygon"
        }
    ]
}